{"1968":[{"country":"Sudan","countRefugee":"20000"}],"1969":[{"country":"Sudan","countRefugee":"20000"}],"1970":[{"country":"Sudan","countRefugee":"21000"}],"1971":[{"country":"Sudan","countRefugee":"22670"},{"country":"Various/Unknown","countRefugee":"60"}],"1972":[{"country":"Sudan","countRefugee":"16080"},{"country":"Various/Unknown","countRefugee":"120"}],"1973":[{"country":"Sudan","countRefugee":"5300"},{"country":"Various/Unknown","countRefugee":"100"}],"1974":[{"country":"Sudan","countRefugee":"5770"},{"country":"Various/Unknown","countRefugee":"140"}],"1975":[{"country":"Sudan","countRefugee":"11000"},{"country":"Various/Unknown","countRefugee":"150"}],"1976":[{"country":"Sudan","countRefugee":"10600"},{"country":"Various/Unknown","countRefugee":"90"}],"1977":[{"country":"Sudan","countRefugee":"10850"},{"country":"Various/Unknown","countRefugee":"90"}],"1978":[{"country":"Sudan","countRefugee":"10850"},{"country":"Various/Unknown","countRefugee":"80"}],"1979":[{"country":"Sudan","countRefugee":"10850"},{"country":"Various/Unknown","countRefugee":"80"}],"1980":[{"country":"Sudan","countRefugee":"10850"},{"country":"Various/Unknown","countRefugee":"80"}],"1981":[{"country":"Sudan","countRefugee":"5350"},{"country":"Various/Unknown","countRefugee":"100"}],"1982":[{"country":"Sudan","countRefugee":"5350"},{"country":"Various/Unknown","countRefugee":"200"}],"1983":[{"country":"Sudan","countRefugee":"31000"},{"country":"Various/Unknown","countRefugee":"370"}],"1984":[{"country":"Sudan","countRefugee":"180000"},{"country":"Various/Unknown","countRefugee":"480"}],"1985":[{"country":"Sudan","countRefugee":"180000"},{"country":"Various/Unknown","countRefugee":"400"}],"1986":[{"country":"Sudan","countRefugee":"132000"},{"country":"Various/Unknown","countRefugee":"400"}],"1987":[{"country":"Sudan","countRefugee":"250000"},{"country":"Somalia","countRefugee":"60000"},{"country":"Various/Unknown","countRefugee":"500"}],"1988":[{"country":"Sudan","countRefugee":"328976"},{"country":"Somalia","countRefugee":"350067"},{"country":"Various/Unknown","countRefugee":"489"}],"1989":[{"country":"Sudan","countRefugee":"384989"},{"country":"Somalia","countRefugee":"324808"},{"country":"Various/Unknown","countRefugee":"369"}],"1990":[{"country":"Sudan","countRefugee":"387585"},{"country":"Somalia","countRefugee":"386000"},{"country":"Various/Unknown","countRefugee":"179"}],"1991":[{"country":"Sudan","countRefugee":"15670"},{"country":"Somalia","countRefugee":"513950"}],"1992":[{"country":"Sudan","countRefugee":"25600"},{"country":"Somalia","countRefugee":"406147"},{"country":"Various/Unknown","countRefugee":"77"}],"1993":[{"country":"Burundi","countRefugee":"24"},{"country":"Dem. Rep. Congo","countRefugee":"13"},{"country":"Djibouti","countRefugee":"26"},{"country":"Kenya","countRefugee":"4"},{"country":"Namibia","countRefugee":"17"},{"country":"Sudan","countRefugee":"44376"},{"country":"Somalia","countRefugee":"228139"},{"country":"Uganda","countRefugee":"19"},{"country":"Various/Unknown","countRefugee":"13"}],"1994":[{"country":"Burundi","countRefugee":"12"},{"country":"Dem. Rep. Congo","countRefugee":"44"},{"country":"Djibouti","countRefugee":"18000"},{"country":"Kenya","countRefugee":"8188"},{"country":"Namibia","countRefugee":"10"},{"country":"Sudan","countRefugee":"51800"},{"country":"Somalia","countRefugee":"269739"},{"country":"Uganda","countRefugee":"111"},{"country":"Various/Unknown","countRefugee":"170"}],"1995":[{"country":"Angola","countRefugee":"5"},{"country":"Burundi","countRefugee":"8"},{"country":"Dem. Rep. Congo","countRefugee":"38"},{"country":"Djibouti","countRefugee":"18000"},{"country":"Kenya","countRefugee":"8680"},{"country":"Rwanda","countRefugee":"61"},{"country":"Sudan","countRefugee":"61113"},{"country":"Somalia","countRefugee":"305351"},{"country":"Uganda","countRefugee":"108"},{"country":"Various/Unknown","countRefugee":"82"},{"country":"Yemen","countRefugee":"33"}],"1996":[{"country":"Angola","countRefugee":"6"},{"country":"Burundi","countRefugee":"11"},{"country":"Dem. Rep. Congo","countRefugee":"41"},{"country":"Djibouti","countRefugee":"18000"},{"country":"Kenya","countRefugee":"8678"},{"country":"Rwanda","countRefugee":"60"},{"country":"Sudan","countRefugee":"75743"},{"country":"Somalia","countRefugee":"287761"},{"country":"Uganda","countRefugee":"109"},{"country":"Various/Unknown","countRefugee":"87"},{"country":"Yemen","countRefugee":"32"}],"1997":[{"country":"Angola","countRefugee":"6"},{"country":"Burundi","countRefugee":"14"},{"country":"Dem. Rep. Congo","countRefugee":"44"},{"country":"Djibouti","countRefugee":"8000"},{"country":"Iraq","countRefugee":"3"},{"country":"Kenya","countRefugee":"8671"},{"country":"Liberia","countRefugee":"1"},{"country":"Libya","countRefugee":"2"},{"country":"Sri Lanka","countRefugee":"1"},{"country":"Rwanda","countRefugee":"64"},{"country":"Sudan","countRefugee":"56868"},{"country":"Somalia","countRefugee":"249235"},{"country":"Slovakia","countRefugee":"1"},{"country":"Chad","countRefugee":"1"},{"country":"United Rep. of Tanzania","countRefugee":"1"},{"country":"Uganda","countRefugee":"29"},{"country":"Various/Unknown","countRefugee":"71"},{"country":"Yemen","countRefugee":"52"},{"country":"South Africa","countRefugee":"3"}],"1998":[{"country":"Angola","countRefugee":"6"},{"country":"Burundi","countRefugee":"14"},{"country":"Dem. Rep. Congo","countRefugee":"42"},{"country":"Czechia","countRefugee":"2"},{"country":"Djibouti","countRefugee":"3000"},{"country":"Iraq","countRefugee":"3"},{"country":"Kenya","countRefugee":"4941"},{"country":"Libya","countRefugee":"1"},{"country":"Sri Lanka","countRefugee":"1"},{"country":"Rwanda","countRefugee":"69"},{"country":"Sudan","countRefugee":"58580"},{"country":"Somalia","countRefugee":"195345"},{"country":"Chad","countRefugee":"2"},{"country":"Uganda","countRefugee":"98"},{"country":"Yemen","countRefugee":"53"},{"country":"South Africa","countRefugee":"3"}],"1999":[{"country":"Angola","countRefugee":"6"},{"country":"Burundi","countRefugee":"15"},{"country":"Dem. Rep. Congo","countRefugee":"40"},{"country":"Czechia","countRefugee":"2"},{"country":"Djibouti","countRefugee":"1503"},{"country":"Iraq","countRefugee":"2"},{"country":"Kenya","countRefugee":"4783"},{"country":"Sri Lanka","countRefugee":"1"},{"country":"Rwanda","countRefugee":"57"},{"country":"Sudan","countRefugee":"70262"},{"country":"Somalia","countRefugee":"180862"},{"country":"Chad","countRefugee":"2"},{"country":"Uganda","countRefugee":"94"},{"country":"Yemen","countRefugee":"56"},{"country":"South Africa","countRefugee":"4"}],"2000":[{"country":"Afghanistan","countRefugee":"3"},{"country":"Angola","countRefugee":"3"},{"country":"Burundi","countRefugee":"17"},{"country":"Dem. Rep. Congo","countAsylum":"16","countRefugee":"43"},{"country":"Czechia","countRefugee":"2"},{"country":"Djibouti","countRefugee":"1560"},{"country":"Eritrea","countRefugee":"3276"},{"country":"Iraq","countAsylum":"1","countRefugee":"2"},{"country":"Kenya","countAsylum":"1","countRefugee":"3"},{"country":"Sri Lanka","countRefugee":"1"},{"country":"Rwanda","countAsylum":"2","countRefugee":"63"},{"country":"Sudan","countRefugee":"71732"},{"country":"Somalia","countRefugee":"121096"},{"country":"Chad","countAsylum":"1","countRefugee":"2"},{"country":"Uganda","countRefugee":"92"},{"country":"Yemen","countAsylum":"17","countRefugee":"61"},{"country":"South Africa","countRefugee":"3"}],"2001":[{"country":"Afghanistan","countRefugee":"3"},{"country":"Angola","countRefugee":"4"},{"country":"Burundi","countRefugee":"16"},{"country":"Dem. Rep. Congo","countAsylum":"2","countRefugee":"53"},{"country":"Czechia","countRefugee":"2"},{"country":"Djibouti","countRefugee":"60"},{"country":"Eritrea","countRefugee":"4212"},{"country":"Iraq","countRefugee":"2"},{"country":"Kenya","countAsylum":"1","countRefugee":"3"},{"country":"Rwanda","countRefugee":"55"},{"country":"Sudan","countRefugee":"80934"},{"country":"Somalia","countRefugee":"67129"},{"country":"Chad","countRefugee":"2"},{"country":"Uganda","countRefugee":"34"},{"country":"Yemen","countRefugee":"41"},{"country":"South Africa","countRefugee":"4"}],"2002":[{"country":"Afghanistan","countRefugee":"3"},{"country":"Angola","countRefugee":"4"},{"country":"Burundi","countAsylum":"4","countRefugee":"23"},{"country":"Central African Rep.","countAsylum":"1"},{"country":"China","countAsylum":"1"},{"country":"Dem. Rep. Congo","countAsylum":"7","countRefugee":"60"},{"country":"Czechia","countRefugee":"2"},{"country":"Djibouti","countRefugee":"55"},{"country":"Eritrea","countRefugee":"5126"},{"country":"Iraq","countRefugee":"5"},{"country":"Kenya","countAsylum":"2","countRefugee":"5"},{"country":"Rwanda","countRefugee":"46"},{"country":"Sudan","countRefugee":"89952"},{"country":"Somalia","countAsylum":"2","countRefugee":"37532"},{"country":"Chad","countRefugee":"2"},{"country":"United Rep. of Tanzania","countAsylum":"1"},{"country":"Uganda","countAsylum":"1","countRefugee":"92"},{"country":"Yemen","countRefugee":"28"},{"country":"South Africa","countRefugee":"5"}],"2003":[{"country":"Afghanistan","countRefugee":"3"},{"country":"Angola","countRefugee":"4"},{"country":"Burundi","countAsylum":"2","countRefugee":"29"},{"country":"Central African Rep.","countAsylum":"1"},{"country":"China","countRefugee":"1"},{"country":"Dem. Rep. Congo","countAsylum":"4","countRefugee":"76"},{"country":"Czechia","countRefugee":"2"},{"country":"Djibouti","countRefugee":"62"},{"country":"Eritrea","countRefugee":"6754"},{"country":"Iraq","countRefugee":"6"},{"country":"Kenya","countRefugee":"5"},{"country":"Rwanda","countRefugee":"37"},{"country":"Sudan","countRefugee":"94899"},{"country":"Somalia","countRefugee":"28276"},{"country":"United Rep. of Tanzania","countAsylum":"1"},{"country":"Uganda","countAsylum":"1","countRefugee":"89"},{"country":"Yemen","countAsylum":"1","countRefugee":"26"},{"country":"South Africa","countRefugee":"5"}],"2004":[{"country":"Afghanistan","countRefugee":"4"},{"country":"Angola","countRefugee":"4"},{"country":"Burundi","countAsylum":"3","countRefugee":"50"},{"country":"China","countRefugee":"1"},{"country":"Cameroon","countAsylum":"4"},{"country":"Dem. Rep. Congo","countAsylum":"32","countRefugee":"82"},{"country":"Czechia","countRefugee":"2"},{"country":"Djibouti","countRefugee":"58"},{"country":"Eritrea","countRefugee":"8719"},{"country":"Iraq","countRefugee":"6"},{"country":"Kenya","countRefugee":"5"},{"country":"Nigeria","countAsylum":"1"},{"country":"Rwanda","countRefugee":"23"},{"country":"Sudan","countRefugee":"90451"},{"country":"Somalia","countRefugee":"16470"},{"country":"Uganda","countRefugee":"82"},{"country":"Yemen","countRefugee":"18"},{"country":"South Africa","countRefugee":"5"}],"2005":[{"country":"Afghanistan","countRefugee":"1"},{"country":"Burundi","countAsylum":"61","countRefugee":"31"},{"country":"China","countRefugee":"1"},{"country":"Cameroon","countAsylum":"4"},{"country":"Dem. Rep. Congo","countAsylum":"130","countRefugee":"122"},{"country":"Czechia","countRefugee":"2"},{"country":"Djibouti","countRefugee":"51"},{"country":"Eritrea","countRefugee":"10700"},{"country":"Nigeria","countAsylum":"5"},{"country":"Rwanda","countAsylum":"7","countRefugee":"22"},{"country":"Sudan","countRefugee":"73927"},{"country":"Somalia","countRefugee":"15901"},{"country":"Uganda","countAsylum":"2","countRefugee":"43"},{"country":"Yemen","countRefugee":"11"},{"country":"South Africa","countRefugee":"5"}],"2006":[{"country":"Afghanistan","countAsylum":"1","countRefugee":"1"},{"country":"Burundi","countAsylum":"67","countRefugee":"50"},{"country":"Belize","countAsylum":"1"},{"country":"Cameroon","countAsylum":"14","countRefugee":"1"},{"country":"Dem. Rep. Congo","countAsylum":"165","countRefugee":"178"},{"country":"Congo","countAsylum":"1"},{"country":"Czechia","countRefugee":"2"},{"country":"Djibouti","countAsylum":"2","countRefugee":"51"},{"country":"Eritrea","countAsylum":"1","countRefugee":"13078"},{"country":"Ghana","countAsylum":"2"},{"country":"Mauritius","countAsylum":"2"},{"country":"Niger","countAsylum":"1"},{"country":"Nigeria","countAsylum":"13"},{"country":"Rwanda","countAsylum":"10","countRefugee":"17"},{"country":"Sudan","countAsylum":"16","countRefugee":"66980"},{"country":"Somalia","countAsylum":"8","countRefugee":"16576"},{"country":"Chad","countAsylum":"4"},{"country":"Togo","countRefugee":"1"},{"country":"United Rep. of Tanzania","countAsylum":"1"},{"country":"Uganda","countAsylum":"7","countRefugee":"38"},{"country":"Yemen","countAsylum":"7","countRefugee":"7"}],"2007":[{"country":"Afghanistan","countAsylum":"0","countRefugee":"1"},{"country":"Burundi","countAsylum":"26","countRefugee":"91"},{"country":"Belize","countAsylum":"1"},{"country":"Cameroon","countAsylum":"18","countRefugee":"3"},{"country":"Dem. Rep. Congo","countAsylum":"63","countRefugee":"230"},{"country":"Congo","countAsylum":"0","countRefugee":"1"},{"country":"Czechia","countRefugee":"2"},{"country":"Djibouti","countRefugee":"55"},{"country":"Eritrea","countAsylum":"5","countRefugee":"20753"},{"country":"Ghana","countAsylum":"2"},{"country":"Guinea-Bissau","countAsylum":"1"},{"country":"Kenya","countAsylum":"0","countRefugee":"2644"},{"country":"Liberia","countAsylum":"2"},{"country":"Mauritius","countAsylum":"2"},{"country":"Niger","countAsylum":"1"},{"country":"Nigeria","countAsylum":"13","countRefugee":"3"},{"country":"Rwanda","countAsylum":"3","countRefugee":"16"},{"country":"Sudan","countAsylum":"14","countRefugee":"35493"},{"country":"Somalia","countAsylum":"13","countRefugee":"25843"},{"country":"Chad","countAsylum":"9"},{"country":"Togo","countRefugee":"1"},{"country":"United Rep. of Tanzania","countAsylum":"1"},{"country":"Uganda","countAsylum":"4","countRefugee":"44"},{"country":"Yemen","countAsylum":"7","countRefugee":"2"},{"country":"Zimbabwe","countAsylum":"0","countRefugee":"1"}],"2008":[{"country":"Afghanistan","countRefugee":"1"},{"country":"Burundi","countAsylum":"61","countRefugee":"54"},{"country":"Belize","countAsylum":"0"},{"country":"Cameroon","countAsylum":"12"},{"country":"Dem. Rep. Congo","countAsylum":"128","countRefugee":"225"},{"country":"Congo","countAsylum":"1"},{"country":"Czechia","countRefugee":"2"},{"country":"Djibouti","countAsylum":"1","countRefugee":"52"},{"country":"Eritrea","countAsylum":"714","countRefugee":"21018"},{"country":"Ghana","countAsylum":"2"},{"country":"Guinea","countRefugee":"1"},{"country":"Guinea-Bissau","countAsylum":"1"},{"country":"Kenya","countRefugee":"2645"},{"country":"Liberia","countAsylum":"2"},{"country":"Mauritius","countAsylum":"1"},{"country":"Niger","countAsylum":"0"},{"country":"Nigeria","countAsylum":"1","countRefugee":"1"},{"country":"Rwanda","countAsylum":"5","countRefugee":"7"},{"country":"Sudan","countAsylum":"10","countRefugee":"25913"},{"country":"Somalia","countAsylum":"710","countRefugee":"33625"},{"country":"Chad","countAsylum":"2"},{"country":"Togo","countRefugee":"1"},{"country":"United Rep. of Tanzania","countAsylum":"0","countRefugee":"1"},{"country":"Uganda","countAsylum":"7","countRefugee":"34"},{"country":"Yemen","countAsylum":"9","countRefugee":"2"},{"country":"Zimbabwe","countRefugee":"1"}],"2009":[{"country":"Afghanistan","countRefugee":"1"},{"country":"Burundi","countAsylum":"22","countRefugee":"78"},{"country":"Cote d'Ivoire","countAsylum":"2"},{"country":"Cameroon","countAsylum":"1"},{"country":"Dem. Rep. Congo","countAsylum":"146","countRefugee":"295"},{"country":"Congo","countAsylum":"5"},{"country":"Czechia","countRefugee":"2"},{"country":"Djibouti","countAsylum":"14","countRefugee":"64"},{"country":"Eritrea","countAsylum":"465","countRefugee":"36164"},{"country":"Ghana","countAsylum":"2"},{"country":"Guinea","countAsylum":"1"},{"country":"Guinea-Bissau","countAsylum":"1"},{"country":"Kenya","countAsylum":"1446","countRefugee":"2732"},{"country":"Liberia","countAsylum":"1"},{"country":"Mauritius","countAsylum":"0"},{"country":"Nigeria","countAsylum":"2"},{"country":"Rwanda","countAsylum":"2","countRefugee":"10"},{"country":"Sudan","countAsylum":"120","countRefugee":"23516"},{"country":"Somalia","countAsylum":"217","countRefugee":"58980"},{"country":"Chad","countAsylum":"1"},{"country":"Togo","countRefugee":"1"},{"country":"United Rep. of Tanzania","countAsylum":"2","countRefugee":"1"},{"country":"Uganda","countAsylum":"6","countRefugee":"32"},{"country":"Yemen","countAsylum":"2","countRefugee":"9"},{"country":"Zimbabwe","countRefugee":"1"}],"2010":[{"country":"Afghanistan","countRefugee":"1"},{"country":"Burundi","countAsylum":"14","countRefugee":"79"},{"country":"Cote d'Ivoire","countAsylum":"0"},{"country":"Cameroon","countAsylum":"1"},{"country":"Dem. Rep. Congo","countAsylum":"108","countRefugee":"383"},{"country":"Congo","countAsylum":"2","countRefugee":"5"},{"country":"Czechia","countRefugee":"2"},{"country":"Djibouti","countAsylum":"10","countRefugee":"62"},{"country":"Eritrea","countAsylum":"143","countRefugee":"44791"},{"country":"Ghana","countAsylum":"2"},{"country":"Guinea","countAsylum":"1"},{"country":"Guinea-Bissau","countAsylum":"1"},{"country":"Kenya","countAsylum":"335","countRefugee":"2425"},{"country":"Liberia","countAsylum":"1"},{"country":"Nigeria","countAsylum":"2"},{"country":"Rwanda","countAsylum":"7","countRefugee":"12"},{"country":"Sudan","countAsylum":"100","countRefugee":"25238"},{"country":"Somalia","countAsylum":"297","countRefugee":"81247"},{"country":"Chad","countAsylum":"1","countRefugee":"1"},{"country":"Togo","countRefugee":"1"},{"country":"United Rep. of Tanzania","countAsylum":"0","countRefugee":"1"},{"country":"Uganda","countAsylum":"2","countRefugee":"34"},{"country":"Yemen","countAsylum":"1","countRefugee":"12"},{"country":"Zimbabwe","countRefugee":"1"}],"2011":[{"country":"Afghanistan","countRefugee":"1"},{"country":"Burundi","countAsylum":"12","countRefugee":"64"},{"country":"Cote d'Ivoire","countAsylum":"1","countRefugee":"3"},{"country":"Cameroon","countAsylum":"1"},{"country":"Dem. Rep. Congo","countAsylum":"30","countRefugee":"534"},{"country":"Congo","countAsylum":"0"},{"country":"Djibouti","countAsylum":"0","countRefugee":"70"},{"country":"Eritrea","countAsylum":"50","countRefugee":"54896"},{"country":"Ghana","countAsylum":"0"},{"country":"Guinea","countAsylum":"1"},{"country":"Guinea-Bissau","countAsylum":"0"},{"country":"Kenya","countAsylum":"303","countRefugee":"2454"},{"country":"Liberia","countAsylum":"4"},{"country":"Nigeria","countAsylum":"0","countRefugee":"2"},{"country":"Rwanda","countAsylum":"7","countRefugee":"13"},{"country":"Sudan","countAsylum":"728","countRefugee":"45286"},{"country":"Somalia","countAsylum":"138","countRefugee":"185466"},{"country":"Chad","countAsylum":"2","countRefugee":"1"},{"country":"United Rep. of Tanzania","countAsylum":"1","countRefugee":"2"},{"country":"Uganda","countAsylum":"2","countRefugee":"29"},{"country":"Yemen","countAsylum":"67","countRefugee":"22"},{"country":"Zimbabwe","countRefugee":"1"}],"2012":[{"country":"Afghanistan","countRefugee":"1"},{"country":"Burundi","countAsylum":"12","countRefugee":"66"},{"country":"Cote d'Ivoire","countAsylum":"0","countRefugee":"3"},{"country":"Cameroon","countAsylum":"0"},{"country":"Dem. Rep. Congo","countAsylum":"149","countRefugee":"582"},{"country":"Congo","countAsylum":"2"},{"country":"Djibouti","countAsylum":"2","countRefugee":"74"},{"country":"Eritrea","countAsylum":"52","countRefugee":"63771"},{"country":"Guinea","countAsylum":"0"},{"country":"Kenya","countAsylum":"2","countRefugee":"2894"},{"country":"Liberia","countAsylum":"3"},{"country":"Nigeria","countRefugee":"2"},{"country":"Rwanda","countAsylum":"6","countRefugee":"12"},{"country":"Saudi Arabia","countAsylum":"1"},{"country":"Sudan","countAsylum":"271","countRefugee":"27175"},{"country":"Somalia","countAsylum":"212","countRefugee":"223031"},{"country":"S. Sudan","countAsylum":"21","countRefugee":"58715"},{"country":"Chad","countAsylum":"1","countRefugee":"1"},{"country":"United Rep. of Tanzania","countAsylum":"0","countRefugee":"2"},{"country":"Uganda","countAsylum":"1","countRefugee":"20"},{"country":"Yemen","countAsylum":"109","countRefugee":"43"},{"country":"Zimbabwe","countRefugee":"1"}],"2013":[{"country":"Afghanistan","countRefugee":"1"},{"country":"Burundi","countAsylum":"21","countRefugee":"59"},{"country":"Cote d'Ivoire","countAsylum":"1","countRefugee":"3"},{"country":"Cameroon","countAsylum":"1"},{"country":"Dem. Rep. Congo","countAsylum":"466","countRefugee":"516"},{"country":"Congo","countAsylum":"3"},{"country":"Djibouti","countAsylum":"2","countRefugee":"75"},{"country":"Egypt","countAsylum":"0","countRefugee":"1"},{"country":"Eritrea","countAsylum":"9","countRefugee":"84377"},{"country":"Iraq","countAsylum":"0","countRefugee":"2"},{"country":"Kenya","countAsylum":"2","countRefugee":"2894"},{"country":"Liberia","countAsylum":"4"},{"country":"Nigeria","countRefugee":"3"},{"country":"Rwanda","countAsylum":"6","countRefugee":"11"},{"country":"Saudi Arabia","countAsylum":"0"},{"country":"Sudan","countAsylum":"309","countRefugee":"33582"},{"country":"Somalia","countAsylum":"7","countRefugee":"240825"},{"country":"S. Sudan","countAsylum":"27","countRefugee":"71506"},{"country":"Chad","countAsylum":"0","countRefugee":"1"},{"country":"United Rep. of Tanzania","countRefugee":"2"},{"country":"Uganda","countAsylum":"1","countRefugee":"20"},{"country":"Yemen","countAsylum":"75","countRefugee":"58"}],"2014":[{"country":"Afghanistan","countAsylum":"0","countRefugee":"1"},{"country":"Burundi","countAsylum":"44","countRefugee":"62"},{"country":"Cote d'Ivoire","countAsylum":"1","countRefugee":"4"},{"country":"Cameroon","countAsylum":"1","countRefugee":"0"},{"country":"Dem. Rep. Congo","countAsylum":"580","countRefugee":"427"},{"country":"Congo","countAsylum":"4","countRefugee":"0"},{"country":"Djibouti","countAsylum":"1","countRefugee":"76"},{"country":"Egypt","countAsylum":"3","countRefugee":"1"},{"country":"Eritrea","countAsylum":"14","countRefugee":"123784"},{"country":"Ethiopia","countAsylum":"0","countRefugee":"0"},{"country":"Iraq","countAsylum":"0","countRefugee":"2"},{"country":"Kenya","countAsylum":"348","countRefugee":"2728"},{"country":"Lebanon","countAsylum":"1","countRefugee":"0"},{"country":"Liberia","countAsylum":"4","countRefugee":"0"},{"country":"Nigeria","countAsylum":"0","countRefugee":"3"},{"country":"Rwanda","countAsylum":"6","countRefugee":"11"},{"country":"Saudi Arabia","countAsylum":"1","countRefugee":"0"},{"country":"Sudan","countAsylum":"278","countRefugee":"35447"},{"country":"Somalia","countAsylum":"2683","countRefugee":"245097"},{"country":"S. Sudan","countAsylum":"65","countRefugee":"251791"},{"country":"Syrian Arab Rep.","countAsylum":"8","countRefugee":"0"},{"country":"Chad","countAsylum":"0","countRefugee":"1"},{"country":"United Rep. of Tanzania","countAsylum":"1","countRefugee":"2"},{"country":"Uganda","countAsylum":"2","countRefugee":"22"},{"country":"Yemen","countAsylum":"79","countRefugee":"65"}],"2015":[{"country":"Afghanistan","countAsylum":"0","countRefugee":"1"},{"country":"Burundi","countAsylum":"56","countRefugee":"52"},{"country":"Cote d'Ivoire","countAsylum":"1","countRefugee":"4"},{"country":"Cameroon","countAsylum":"1","countRefugee":"0"},{"country":"Dem. Rep. Congo","countAsylum":"620","countRefugee":"426"},{"country":"Congo","countAsylum":"1","countRefugee":"0"},{"country":"Cuba","countAsylum":"3","countRefugee":"0"},{"country":"Djibouti","countAsylum":"1","countRefugee":"76"},{"country":"Egypt","countAsylum":"0","countRefugee":"4"},{"country":"Eritrea","countAsylum":"0","countRefugee":"155231"},{"country":"Iran (Islamic Rep. of)","countAsylum":"1","countRefugee":"0"},{"country":"Iraq","countAsylum":"7","countRefugee":"2"},{"country":"Kenya","countAsylum":"346","countRefugee":"3193"},{"country":"Lebanon","countAsylum":"1","countRefugee":"0"},{"country":"Liberia","countAsylum":"4","countRefugee":"0"},{"country":"Nigeria","countAsylum":"0","countRefugee":"1"},{"country":"Rwanda","countAsylum":"6","countRefugee":"11"},{"country":"Saudi Arabia","countAsylum":"1","countRefugee":"0"},{"country":"Sudan","countAsylum":"386","countRefugee":"37785"},{"country":"Somalia","countAsylum":"0","countRefugee":"256669"},{"country":"S. Sudan","countAsylum":"439","countRefugee":"281508"},{"country":"Syrian Arab Rep.","countAsylum":"15","countRefugee":"9"},{"country":"Chad","countAsylum":"1","countRefugee":"1"},{"country":"United Rep. of Tanzania","countAsylum":"1","countRefugee":"2"},{"country":"Uganda","countAsylum":"4","countRefugee":"23"},{"country":"Yemen","countAsylum":"236","countRefugee":"1088"}],"2016":[{"country":"Afghanistan","countAsylum":"0","countRefugee":"*"},{"country":"Burundi","countAsylum":"63","countRefugee":"57"},{"country":"Cote d'Ivoire","countAsylum":"*","countRefugee":"*"},{"country":"Cameroon","countAsylum":"*","countRefugee":"0"},{"country":"Dem. Rep. Congo","countAsylum":"587","countRefugee":"444"},{"country":"Congo","countAsylum":"*","countRefugee":"0"},{"country":"Cuba","countAsylum":"0","countRefugee":"*"},{"country":"Djibouti","countAsylum":"*","countRefugee":"81"},{"country":"Egypt","countAsylum":"0","countRefugee":"*"},{"country":"Eritrea","countAsylum":"78","countRefugee":"165548"},{"country":"Ethiopia","countAsylum":"0","countRefugee":"0"},{"country":"Iran (Islamic Rep. of)","countAsylum":"*","countRefugee":"0"},{"country":"Iraq","countAsylum":"*","countRefugee":"10"},{"country":"Kenya","countAsylum":"412","countRefugee":"3326"},{"country":"Lebanon","countAsylum":"*","countRefugee":"0"},{"country":"Nigeria","countAsylum":"*","countRefugee":"*"},{"country":"Russia","countAsylum":"*","countRefugee":"0"},{"country":"Rwanda","countAsylum":"6","countRefugee":"11"},{"country":"Saudi Arabia","countAsylum":"*","countRefugee":"0"},{"country":"Sudan","countAsylum":"447","countRefugee":"39896"},{"country":"Somalia","countAsylum":"79","countRefugee":"242014"},{"country":"S. Sudan","countAsylum":"47","countRefugee":"338774"},{"country":"Syrian Arab Rep.","countAsylum":"48","countRefugee":"9"},{"country":"Chad","countAsylum":"*","countRefugee":"*"},{"country":"United Rep. of Tanzania","countAsylum":"*","countRefugee":"*"},{"country":"Uganda","countAsylum":"5","countRefugee":"23"},{"country":"Yemen","countAsylum":"176","countRefugee":"1423"}]}