{"1976":[{"country":"Namibia","countRefugee":"50"}],"1977":[{"country":"Namibia","countRefugee":"50"},{"country":"Various/Unknown","countRefugee":"90"},{"country":"South Africa","countRefugee":"160"}],"1978":[{"country":"Various/Unknown","countRefugee":"370"}],"1979":[{"country":"Various/Unknown","countRefugee":"180"},{"country":"South Africa","countRefugee":"110"},{"country":"Zimbabwe","countRefugee":"110"}],"1980":[{"country":"Chad","countRefugee":"100000"}],"1981":[{"country":"Chad","countRefugee":"84570"},{"country":"Various/Unknown","countRefugee":"5000"}],"1982":[{"country":"Ghana","countRefugee":"110"},{"country":"Iran (Islamic Rep. of)","countRefugee":"80"},{"country":"Namibia","countRefugee":"50"},{"country":"Chad","countRefugee":"4000"},{"country":"Various/Unknown","countRefugee":"1000"}],"1983":[{"country":"Ethiopia","countRefugee":"50"},{"country":"Ghana","countRefugee":"320"},{"country":"Iran (Islamic Rep. of)","countRefugee":"90"},{"country":"Namibia","countRefugee":"70"},{"country":"Chad","countRefugee":"4000"},{"country":"Various/Unknown","countRefugee":"90"}],"1984":[{"country":"Ghana","countRefugee":"350"},{"country":"Iran (Islamic Rep. of)","countRefugee":"90"},{"country":"Chad","countRefugee":"4000"},{"country":"Various/Unknown","countRefugee":"130"}],"1985":[{"country":"Ethiopia","countRefugee":"60"},{"country":"Ghana","countRefugee":"360"},{"country":"Iran (Islamic Rep. of)","countRefugee":"90"},{"country":"Sri Lanka","countRefugee":"150"},{"country":"Namibia","countRefugee":"120"},{"country":"Chad","countRefugee":"5000"},{"country":"Various/Unknown","countRefugee":"100"}],"1986":[{"country":"Ghana","countRefugee":"270"},{"country":"Iran (Islamic Rep. of)","countRefugee":"60"},{"country":"Sri Lanka","countRefugee":"160"},{"country":"Namibia","countRefugee":"120"},{"country":"Chad","countRefugee":"4020"},{"country":"Various/Unknown","countRefugee":"130"}],"1987":[{"country":"Ethiopia","countRefugee":"50"},{"country":"Ghana","countRefugee":"280"},{"country":"Iran (Islamic Rep. of)","countRefugee":"70"},{"country":"Sri Lanka","countRefugee":"160"},{"country":"Namibia","countRefugee":"120"},{"country":"Chad","countRefugee":"4310"},{"country":"Various/Unknown","countRefugee":"110"}],"1988":[{"country":"Ethiopia","countRefugee":"60"},{"country":"Ghana","countRefugee":"360"},{"country":"Iran (Islamic Rep. of)","countRefugee":"70"},{"country":"Sri Lanka","countRefugee":"60"},{"country":"Namibia","countRefugee":"130"},{"country":"Chad","countRefugee":"4283"},{"country":"Various/Unknown","countRefugee":"150"},{"country":"South Africa","countRefugee":"60"}],"1989":[{"country":"Ethiopia","countRefugee":"50"},{"country":"Ghana","countRefugee":"190"},{"country":"Namibia","countRefugee":"100"},{"country":"Chad","countRefugee":"3311"},{"country":"Various/Unknown","countRefugee":"130"}],"1990":[{"country":"Ethiopia","countRefugee":"50"},{"country":"Ghana","countRefugee":"166"},{"country":"Liberia","countRefugee":"1600"},{"country":"Namibia","countRefugee":"70"},{"country":"Chad","countRefugee":"1555"},{"country":"Various/Unknown","countRefugee":"130"}],"1991":[{"country":"Ethiopia","countRefugee":"50"},{"country":"Ghana","countRefugee":"156"},{"country":"Liberia","countRefugee":"1690"},{"country":"Namibia","countRefugee":"50"},{"country":"Chad","countRefugee":"1477"},{"country":"Various/Unknown","countRefugee":"150"}],"1992":[{"country":"Ethiopia","countRefugee":"50"},{"country":"Ghana","countRefugee":"148"},{"country":"Liberia","countRefugee":"2934"},{"country":"Chad","countRefugee":"1420"},{"country":"Various/Unknown","countRefugee":"230"}],"1993":[{"country":"Angola","countRefugee":"10"},{"country":"Benin","countRefugee":"23"},{"country":"Burkina Faso","countRefugee":"1"},{"country":"Bangladesh","countRefugee":"1"},{"country":"Central African Rep.","countRefugee":"7"},{"country":"Cote d'Ivoire","countRefugee":"2"},{"country":"Cameroon","countRefugee":"18"},{"country":"Dem. Rep. Congo","countRefugee":"53"},{"country":"Congo","countRefugee":"1"},{"country":"Algeria","countRefugee":"1"},{"country":"Ethiopia","countRefugee":"44"},{"country":"Ghana","countRefugee":"143"},{"country":"Hungary","countRefugee":"2"},{"country":"Lebanon","countRefugee":"1"},{"country":"Liberia","countRefugee":"2935"},{"country":"Sri Lanka","countRefugee":"22"},{"country":"Namibia","countRefugee":"15"},{"country":"Palestinian","countRefugee":"6"},{"country":"Russia","countRefugee":"6"},{"country":"Rwanda","countRefugee":"7"},{"country":"Sudan","countRefugee":"41"},{"country":"Sierra Leone","countRefugee":"1"},{"country":"Somalia","countRefugee":"41"},{"country":"Chad","countRefugee":"1419"},{"country":"Togo","countRefugee":"19"},{"country":"South Africa","countRefugee":"10"}],"1994":[{"country":"Angola","countRefugee":"10"},{"country":"Benin","countRefugee":"23"},{"country":"Burkina Faso","countRefugee":"3"},{"country":"Central African Rep.","countRefugee":"8"},{"country":"Cote d'Ivoire","countRefugee":"3"},{"country":"Cameroon","countRefugee":"19"},{"country":"Dem. Rep. Congo","countRefugee":"59"},{"country":"Congo","countRefugee":"3"},{"country":"Algeria","countRefugee":"1"},{"country":"Ethiopia","countRefugee":"42"},{"country":"Ghana","countRefugee":"136"},{"country":"Hungary","countRefugee":"2"},{"country":"Lebanon","countRefugee":"1"},{"country":"Liberia","countRefugee":"4097"},{"country":"Sri Lanka","countRefugee":"21"},{"country":"Mali","countRefugee":"2"},{"country":"Namibia","countRefugee":"7"},{"country":"Palestinian","countRefugee":"6"},{"country":"Rwanda","countRefugee":"12"},{"country":"Sudan","countRefugee":"66"},{"country":"Sierra Leone","countRefugee":"1"},{"country":"Somalia","countRefugee":"49"},{"country":"Chad","countRefugee":"1418"},{"country":"Togo","countRefugee":"22"},{"country":"Uganda","countRefugee":"6"},{"country":"South Africa","countRefugee":"9"}],"1995":[{"country":"Benin","countRefugee":"23"},{"country":"Cameroon","countRefugee":"1307"},{"country":"Dem. Rep. Congo","countRefugee":"50"},{"country":"Ethiopia","countRefugee":"40"},{"country":"Ghana","countRefugee":"133"},{"country":"Liberia","countRefugee":"4931"},{"country":"Sudan","countRefugee":"53"},{"country":"Somalia","countRefugee":"51"},{"country":"Chad","countRefugee":"1418"},{"country":"Various/Unknown","countRefugee":"112"}],"1996":[{"country":"Benin","countRefugee":"23"},{"country":"Cameroon","countRefugee":"1307"},{"country":"Dem. Rep. Congo","countRefugee":"57"},{"country":"Ethiopia","countRefugee":"41"},{"country":"Ghana","countRefugee":"125"},{"country":"Liberia","countRefugee":"5278"},{"country":"Sudan","countRefugee":"72"},{"country":"Somalia","countRefugee":"51"},{"country":"Chad","countRefugee":"1416"},{"country":"Various/Unknown","countRefugee":"116"}],"1997":[{"country":"Angola","countRefugee":"13"},{"country":"Benin","countRefugee":"23"},{"country":"Central African Rep.","countRefugee":"8"},{"country":"Cameroon","countRefugee":"1313"},{"country":"Dem. Rep. Congo","countRefugee":"96"},{"country":"Ethiopia","countRefugee":"53"},{"country":"Ghana","countRefugee":"132"},{"country":"Liberia","countRefugee":"4909"},{"country":"Sri Lanka","countRefugee":"20"},{"country":"Palestinian","countRefugee":"6"},{"country":"Rwanda","countRefugee":"26"},{"country":"Sudan","countRefugee":"105"},{"country":"Sierra Leone","countRefugee":"768"},{"country":"Somalia","countRefugee":"51"},{"country":"Chad","countRefugee":"1455"},{"country":"Togo","countRefugee":"17"},{"country":"Uganda","countRefugee":"6"},{"country":"Various/Unknown","countRefugee":"61"},{"country":"South Africa","countRefugee":"9"}],"1998":[{"country":"Angola","countRefugee":"13"},{"country":"Benin","countRefugee":"23"},{"country":"Central African Rep.","countRefugee":"8"},{"country":"Cameroon","countRefugee":"3"},{"country":"Dem. Rep. Congo","countRefugee":"62"},{"country":"Ethiopia","countRefugee":"54"},{"country":"Ghana","countRefugee":"132"},{"country":"Liberia","countRefugee":"1708"},{"country":"Sri Lanka","countRefugee":"20"},{"country":"Palestinian","countRefugee":"6"},{"country":"Rwanda","countRefugee":"9"},{"country":"Sudan","countRefugee":"68"},{"country":"Sierra Leone","countRefugee":"1195"},{"country":"Somalia","countRefugee":"51"},{"country":"Chad","countRefugee":"3188"},{"country":"Togo","countRefugee":"21"},{"country":"Various/Unknown","countRefugee":"210"},{"country":"South Africa","countRefugee":"9"}],"1999":[{"country":"Angola","countRefugee":"13"},{"country":"Benin","countRefugee":"23"},{"country":"Cameroon","countRefugee":"4"},{"country":"Dem. Rep. Congo","countRefugee":"70"},{"country":"Liberia","countRefugee":"1569"},{"country":"Sudan","countRefugee":"74"},{"country":"Sierra Leone","countRefugee":"1702"},{"country":"Chad","countRefugee":"3194"},{"country":"Various/Unknown","countRefugee":"292"}],"2000":[{"country":"Angola","countRefugee":"14"},{"country":"Benin","countRefugee":"23"},{"country":"Cameroon","countRefugee":"4"},{"country":"Congo","countRefugee":"70"},{"country":"Liberia","countRefugee":"1588"},{"country":"Sudan","countRefugee":"78"},{"country":"Sierra Leone","countRefugee":"2001"},{"country":"Chad","countRefugee":"3194"},{"country":"Various/Unknown","countRefugee":"298"}],"2001":[{"country":"Angola","countRefugee":"14"},{"country":"Benin","countRefugee":"23"},{"country":"Central African Rep.","countAsylum":"3","countRefugee":"14"},{"country":"Cameroon","countAsylum":"3","countRefugee":"4"},{"country":"Congo","countAsylum":"4","countRefugee":"48"},{"country":"Eritrea","countRefugee":"20"},{"country":"Ethiopia","countAsylum":"2","countRefugee":"8"},{"country":"Ghana","countRefugee":"87"},{"country":"Guinea","countRefugee":"12"},{"country":"Eq. Guinea","countRefugee":"12"},{"country":"Liberia","countAsylum":"75","countRefugee":"1505"},{"country":"Sri Lanka","countRefugee":"24"},{"country":"Namibia","countRefugee":"35"},{"country":"Palestinian","countRefugee":"24"},{"country":"Rwanda","countAsylum":"7","countRefugee":"24"},{"country":"Sudan","countAsylum":"3","countRefugee":"72"},{"country":"Sierra Leone","countAsylum":"30","countRefugee":"2041"},{"country":"Chad","countAsylum":"5","countRefugee":"3193"},{"country":"Togo","countRefugee":"40"}],"2002":[{"country":"Angola","countAsylum":"1","countRefugee":"14"},{"country":"Burundi","countAsylum":"1"},{"country":"Benin","countRefugee":"23"},{"country":"Central African Rep.","countAsylum":"2","countRefugee":"14"},{"country":"Cote d'Ivoire","countAsylum":"1","countRefugee":"2"},{"country":"Cameroon","countAsylum":"4","countRefugee":"7"},{"country":"Dem. Rep. Congo","countAsylum":"1"},{"country":"Congo","countRefugee":"55"},{"country":"Eritrea","countRefugee":"20"},{"country":"Ethiopia","countRefugee":"9"},{"country":"Ghana","countRefugee":"86"},{"country":"Guinea","countRefugee":"12"},{"country":"Eq. Guinea","countRefugee":"12"},{"country":"Liberia","countAsylum":"13","countRefugee":"1792"},{"country":"Sri Lanka","countRefugee":"24"},{"country":"Namibia","countRefugee":"35"},{"country":"Palestinian","countRefugee":"24"},{"country":"Rwanda","countRefugee":"27"},{"country":"Sudan","countAsylum":"7","countRefugee":"80"},{"country":"Sierra Leone","countRefugee":"1877"},{"country":"Somalia","countRefugee":"8"},{"country":"Chad","countRefugee":"3194"},{"country":"Togo","countRefugee":"40"}],"2003":[{"country":"Angola","countAsylum":"3","countRefugee":"13"},{"country":"Burundi","countAsylum":"2","countRefugee":"1"},{"country":"Central African Rep.","countAsylum":"3","countRefugee":"14"},{"country":"Cote d'Ivoire","countAsylum":"21","countRefugee":"3"},{"country":"Cameroon","countAsylum":"47","countRefugee":"7"},{"country":"Dem. Rep. Congo","countAsylum":"6","countRefugee":"105"},{"country":"Congo","countAsylum":"2","countRefugee":"3"},{"country":"Eritrea","countRefugee":"21"},{"country":"Ethiopia","countRefugee":"14"},{"country":"Ghana","countAsylum":"1","countRefugee":"86"},{"country":"Guinea","countAsylum":"1","countRefugee":"12"},{"country":"Eq. Guinea","countRefugee":"12"},{"country":"Liberia","countAsylum":"1005","countRefugee":"3674"},{"country":"Libya","countRefugee":"1"},{"country":"Sri Lanka","countAsylum":"1","countRefugee":"24"},{"country":"Namibia","countRefugee":"35"},{"country":"Palestinian","countRefugee":"24"},{"country":"Rwanda","countAsylum":"1","countRefugee":"24"},{"country":"Sudan","countAsylum":"8","countRefugee":"102"},{"country":"Sierra Leone","countAsylum":"23","countRefugee":"1756"},{"country":"Somalia","countRefugee":"7"},{"country":"Chad","countAsylum":"1","countRefugee":"3193"},{"country":"Togo","countRefugee":"40"}],"2004":[{"country":"Angola","countAsylum":"3","countRefugee":"13"},{"country":"Burundi","countAsylum":"2","countRefugee":"1"},{"country":"Central African Rep.","countAsylum":"1","countRefugee":"14"},{"country":"Cote d'Ivoire","countAsylum":"31","countRefugee":"12"},{"country":"Cameroon","countAsylum":"2","countRefugee":"54"},{"country":"Dem. Rep. Congo","countAsylum":"64","countRefugee":"133"},{"country":"Congo","countAsylum":"2","countRefugee":"3"},{"country":"Eritrea","countRefugee":"21"},{"country":"Ethiopia","countRefugee":"14"},{"country":"Ghana","countAsylum":"2","countRefugee":"87"},{"country":"Guinea","countAsylum":"1","countRefugee":"12"},{"country":"Eq. Guinea","countRefugee":"12"},{"country":"Liberia","countAsylum":"933","countRefugee":"2932"},{"country":"Libya","countRefugee":"1"},{"country":"Sri Lanka","countAsylum":"1","countRefugee":"24"},{"country":"Namibia","countRefugee":"35"},{"country":"Palestinian","countRefugee":"24"},{"country":"Rwanda","countRefugee":"24"},{"country":"Sudan","countAsylum":"14","countRefugee":"104"},{"country":"Sierra Leone","countAsylum":"22","countRefugee":"1633"},{"country":"Somalia","countRefugee":"7"},{"country":"Chad","countAsylum":"8","countRefugee":"3195"},{"country":"Togo","countRefugee":"40"}],"2005":[{"country":"Angola","countAsylum":"2","countRefugee":"8"},{"country":"Burundi","countAsylum":"2","countRefugee":"6"},{"country":"Central African Rep.","countRefugee":"6"},{"country":"Cote d'Ivoire","countAsylum":"37","countRefugee":"42"},{"country":"Cameroon","countAsylum":"1","countRefugee":"56"},{"country":"Dem. Rep. Congo","countAsylum":"175","countRefugee":"703"},{"country":"Congo","countAsylum":"2","countRefugee":"3"},{"country":"Eritrea","countAsylum":"1","countRefugee":"10"},{"country":"Ethiopia","countAsylum":"1","countRefugee":"33"},{"country":"Ghana","countAsylum":"2","countRefugee":"70"},{"country":"Guinea","countAsylum":"7","countRefugee":"23"},{"country":"Guinea-Bissau","countRefugee":"6"},{"country":"Eq. Guinea","countRefugee":"4"},{"country":"Liberia","countAsylum":"118","countRefugee":"6051"},{"country":"Libya","countRefugee":"1"},{"country":"Sri Lanka","countAsylum":"1","countRefugee":"12"},{"country":"Palestinian","countRefugee":"2"},{"country":"Rwanda","countAsylum":"1","countRefugee":"38"},{"country":"Sudan","countAsylum":"9","countRefugee":"173"},{"country":"Sierra Leone","countAsylum":"46","countRefugee":"1670"},{"country":"Somalia","countRefugee":"27"},{"country":"Chad","countAsylum":"8","countRefugee":"61"},{"country":"Togo","countAsylum":"7","countRefugee":"12"},{"country":"Uganda","countRefugee":"2"}],"2006":[{"country":"Angola","countRefugee":"8"},{"country":"Burundi","countRefugee":"6"},{"country":"Central African Rep.","countAsylum":"1","countRefugee":"6"},{"country":"Cote d'Ivoire","countAsylum":"28","countRefugee":"43"},{"country":"Cameroon","countAsylum":"10","countRefugee":"28"},{"country":"Dem. Rep. Congo","countAsylum":"352","countRefugee":"750"},{"country":"Congo","countAsylum":"2","countRefugee":"2"},{"country":"Eritrea","countAsylum":"1","countRefugee":"10"},{"country":"Ethiopia","countAsylum":"1","countRefugee":"33"},{"country":"Ghana","countRefugee":"69"},{"country":"Guinea","countAsylum":"9","countRefugee":"24"},{"country":"Guinea-Bissau","countRefugee":"5"},{"country":"Eq. Guinea","countRefugee":"4"},{"country":"Liberia","countAsylum":"174","countRefugee":"5778"},{"country":"Libya","countRefugee":"1"},{"country":"Sri Lanka","countRefugee":"13"},{"country":"Mozambique","countRefugee":"1"},{"country":"Niger","countAsylum":"1"},{"country":"Palestinian","countRefugee":"2"},{"country":"Rwanda","countAsylum":"2","countRefugee":"35"},{"country":"Sudan","countAsylum":"8","countRefugee":"181"},{"country":"Sierra Leone","countAsylum":"63","countRefugee":"1667"},{"country":"Somalia","countRefugee":"24"},{"country":"Syrian Arab Rep.","countAsylum":"1"},{"country":"Chad","countAsylum":"7","countRefugee":"62"},{"country":"Togo","countAsylum":"16","countRefugee":"14"},{"country":"Uganda","countRefugee":"2"}],"2007":[{"country":"Angola","countRefugee":"8"},{"country":"Burundi","countRefugee":"6"},{"country":"Central African Rep.","countAsylum":"5","countRefugee":"7"},{"country":"Cote d'Ivoire","countAsylum":"19","countRefugee":"39"},{"country":"Cameroon","countAsylum":"51","countRefugee":"28"},{"country":"Dem. Rep. Congo","countAsylum":"327","countRefugee":"761"},{"country":"Congo","countAsylum":"5","countRefugee":"3"},{"country":"Eritrea","countAsylum":"2","countRefugee":"10"},{"country":"Ethiopia","countAsylum":"0","countRefugee":"33"},{"country":"Ghana","countAsylum":"1","countRefugee":"69"},{"country":"Guinea","countAsylum":"6","countRefugee":"25"},{"country":"Guinea-Bissau","countAsylum":"0","countRefugee":"5"},{"country":"Eq. Guinea","countAsylum":"0","countRefugee":"4"},{"country":"Lebanon","countAsylum":"3"},{"country":"Liberia","countAsylum":"173","countRefugee":"5528"},{"country":"Libya","countRefugee":"1"},{"country":"Sri Lanka","countRefugee":"13"},{"country":"Niger","countAsylum":"1"},{"country":"Palestinian","countRefugee":"6"},{"country":"Rwanda","countAsylum":"1","countRefugee":"36"},{"country":"Sudan","countAsylum":"17","countRefugee":"172"},{"country":"Sierra Leone","countAsylum":"63","countRefugee":"1606"},{"country":"Somalia","countRefugee":"25"},{"country":"Syrian Arab Rep.","countAsylum":"0"},{"country":"Chad","countAsylum":"16","countRefugee":"57"},{"country":"Togo","countAsylum":"10","countRefugee":"14"},{"country":"Uganda","countRefugee":"4"}],"2008":[{"country":"Angola","countRefugee":"8"},{"country":"Burundi","countRefugee":"6"},{"country":"Central African Rep.","countAsylum":"9","countRefugee":"7"},{"country":"Cote d'Ivoire","countAsylum":"33","countRefugee":"36"},{"country":"Cameroon","countAsylum":"61","countRefugee":"1819"},{"country":"Dem. Rep. Congo","countAsylum":"707","countRefugee":"773"},{"country":"Congo","countAsylum":"7","countRefugee":"3"},{"country":"Eritrea","countAsylum":"4","countRefugee":"10"},{"country":"Ethiopia","countAsylum":"3","countRefugee":"29"},{"country":"Gabon","countAsylum":"1"},{"country":"Ghana","countAsylum":"2","countRefugee":"69"},{"country":"Guinea","countAsylum":"12","countRefugee":"25"},{"country":"Guinea-Bissau","countAsylum":"1","countRefugee":"5"},{"country":"Eq. Guinea","countRefugee":"4"},{"country":"Lebanon","countAsylum":"6"},{"country":"Liberia","countAsylum":"205","countRefugee":"5303"},{"country":"Libya","countRefugee":"1"},{"country":"Sri Lanka","countRefugee":"13"},{"country":"Palestinian","countAsylum":"1","countRefugee":"6"},{"country":"Rwanda","countAsylum":"3","countRefugee":"36"},{"country":"Sudan","countAsylum":"23","countRefugee":"188"},{"country":"Sierra Leone","countAsylum":"111","countRefugee":"1634"},{"country":"Somalia","countAsylum":"2","countRefugee":"19"},{"country":"Chad","countAsylum":"12","countRefugee":"112"},{"country":"Togo","countAsylum":"15","countRefugee":"14"},{"country":"Uganda","countRefugee":"4"}],"2009":[{"country":"Angola","countRefugee":"8"},{"country":"Burundi","countRefugee":"6"},{"country":"Benin","countAsylum":"1"},{"country":"Central African Rep.","countAsylum":"5","countRefugee":"7"},{"country":"Cote d'Ivoire","countAsylum":"14","countRefugee":"36"},{"country":"Cameroon","countAsylum":"39","countRefugee":"1995"},{"country":"Dem. Rep. Congo","countAsylum":"974","countRefugee":"760"},{"country":"Congo","countAsylum":"8","countRefugee":"3"},{"country":"Eritrea","countAsylum":"4","countRefugee":"10"},{"country":"Ethiopia","countAsylum":"3","countRefugee":"29"},{"country":"Gabon","countAsylum":"1"},{"country":"Ghana","countAsylum":"1","countRefugee":"69"},{"country":"Guinea","countAsylum":"12","countRefugee":"25"},{"country":"Guinea-Bissau","countAsylum":"1","countRefugee":"5"},{"country":"Eq. Guinea","countRefugee":"4"},{"country":"Lebanon","countAsylum":"0"},{"country":"Liberia","countAsylum":"25","countRefugee":"5261"},{"country":"Libya","countRefugee":"1"},{"country":"Sri Lanka","countRefugee":"16"},{"country":"Niger","countRefugee":"1"},{"country":"Palestinian","countAsylum":"2","countRefugee":"6"},{"country":"Rwanda","countAsylum":"3","countRefugee":"35"},{"country":"Sudan","countAsylum":"9","countRefugee":"178"},{"country":"Sierra Leone","countAsylum":"13","countRefugee":"456"},{"country":"Somalia","countAsylum":"1","countRefugee":"20"},{"country":"Chad","countAsylum":"24","countRefugee":"178"},{"country":"Togo","countAsylum":"5","countRefugee":"14"},{"country":"Uganda","countRefugee":"4"}],"2010":[{"country":"Angola","countRefugee":"7"},{"country":"Burundi","countRefugee":"6"},{"country":"Belgium","countAsylum":"1"},{"country":"Benin","countAsylum":"1"},{"country":"Central African Rep.","countAsylum":"9","countRefugee":"7"},{"country":"Cote d'Ivoire","countAsylum":"24","countRefugee":"36"},{"country":"Cameroon","countAsylum":"47","countRefugee":"1998"},{"country":"Dem. Rep. Congo","countAsylum":"1202","countRefugee":"720"},{"country":"Congo","countAsylum":"9","countRefugee":"4"},{"country":"Eritrea","countAsylum":"7","countRefugee":"12"},{"country":"Ethiopia","countAsylum":"1","countRefugee":"29"},{"country":"Gabon","countAsylum":"1"},{"country":"Ghana","countAsylum":"3","countRefugee":"69"},{"country":"Guinea","countAsylum":"19","countRefugee":"43"},{"country":"Guinea-Bissau","countAsylum":"1","countRefugee":"6"},{"country":"Eq. Guinea","countRefugee":"4"},{"country":"Iraq","countAsylum":"2"},{"country":"Liberia","countAsylum":"29","countRefugee":"5316"},{"country":"Libya","countRefugee":"1"},{"country":"Sri Lanka","countRefugee":"16"},{"country":"Mali","countRefugee":"1"},{"country":"Niger","countRefugee":"1"},{"country":"Palestinian","countAsylum":"2","countRefugee":"6"},{"country":"Rwanda","countAsylum":"3","countRefugee":"36"},{"country":"Sudan","countAsylum":"38","countRefugee":"154"},{"country":"Sierra Leone","countAsylum":"1","countRefugee":"58"},{"country":"Somalia","countAsylum":"0","countRefugee":"20"},{"country":"Chad","countAsylum":"401","countRefugee":"178"},{"country":"Togo","countAsylum":"14","countRefugee":"17"},{"country":"Uganda","countRefugee":"2"}],"2011":[{"country":"Angola","countRefugee":"7"},{"country":"Burundi","countRefugee":"6"},{"country":"Belgium","countAsylum":"0"},{"country":"Benin","countAsylum":"0"},{"country":"Central African Rep.","countAsylum":"5","countRefugee":"7"},{"country":"Cote d'Ivoire","countAsylum":"126","countRefugee":"37"},{"country":"Cameroon","countAsylum":"19","countRefugee":"1997"},{"country":"Dem. Rep. Congo","countAsylum":"884","countRefugee":"798"},{"country":"Congo","countAsylum":"5","countRefugee":"4"},{"country":"Egypt","countAsylum":"3"},{"country":"Eritrea","countAsylum":"7","countRefugee":"13"},{"country":"Ethiopia","countAsylum":"2","countRefugee":"29"},{"country":"Gabon","countAsylum":"1"},{"country":"Ghana","countAsylum":"4","countRefugee":"69"},{"country":"Guinea","countAsylum":"26","countRefugee":"44"},{"country":"Guinea-Bissau","countAsylum":"1","countRefugee":"5"},{"country":"Eq. Guinea","countRefugee":"4"},{"country":"Iraq","countAsylum":"0"},{"country":"Liberia","countAsylum":"27","countRefugee":"5299"},{"country":"Libya","countRefugee":"1"},{"country":"Sri Lanka","countRefugee":"16"},{"country":"Mali","countRefugee":"1"},{"country":"Niger","countRefugee":"1"},{"country":"Palestinian","countAsylum":"0","countRefugee":"7"},{"country":"Rwanda","countAsylum":"2","countRefugee":"36"},{"country":"Sudan","countAsylum":"15","countRefugee":"149"},{"country":"Sierra Leone","countAsylum":"0","countRefugee":"57"},{"country":"Somalia","countRefugee":"21"},{"country":"Chad","countAsylum":"391","countRefugee":"179"},{"country":"Togo","countAsylum":"11","countRefugee":"17"},{"country":"Uganda","countRefugee":"2"}],"2012":[{"country":"Angola","countRefugee":"7"},{"country":"Burundi","countAsylum":"4","countRefugee":"6"},{"country":"Belgium","countAsylum":"1"},{"country":"Central African Rep.","countAsylum":"5","countRefugee":"7"},{"country":"Cote d'Ivoire","countAsylum":"33","countRefugee":"148"},{"country":"Cameroon","countAsylum":"17","countRefugee":"858"},{"country":"Dem. Rep. Congo","countAsylum":"612","countRefugee":"860"},{"country":"Congo","countAsylum":"0","countRefugee":"4"},{"country":"Egypt","countAsylum":"0","countRefugee":"3"},{"country":"Eritrea","countAsylum":"4","countRefugee":"15"},{"country":"Ethiopia","countAsylum":"0","countRefugee":"29"},{"country":"Gabon","countAsylum":"0"},{"country":"Ghana","countAsylum":"2","countRefugee":"71"},{"country":"Guinea","countAsylum":"18","countRefugee":"44"},{"country":"Gambia","countAsylum":"1"},{"country":"Guinea-Bissau","countAsylum":"0","countRefugee":"6"},{"country":"Eq. Guinea","countRefugee":"4"},{"country":"Iraq","countAsylum":"0","countRefugee":"2"},{"country":"Liberia","countAsylum":"6","countRefugee":"564"},{"country":"Libya","countRefugee":"2"},{"country":"Sri Lanka","countRefugee":"15"},{"country":"Mali","countAsylum":"7","countRefugee":"9"},{"country":"Niger","countRefugee":"1"},{"country":"Palestinian","countRefugee":"7"},{"country":"Rwanda","countAsylum":"1","countRefugee":"36"},{"country":"Sudan","countAsylum":"8","countRefugee":"146"},{"country":"Sierra Leone","countRefugee":"50"},{"country":"Somalia","countRefugee":"21"},{"country":"Syrian Arab Rep.","countAsylum":"1"},{"country":"Chad","countAsylum":"316","countRefugee":"213"},{"country":"Togo","countAsylum":"6","countRefugee":"24"},{"country":"Uganda","countRefugee":"2"}],"2013":[{"country":"Afghanistan","countAsylum":"0","countRefugee":"5"},{"country":"Burundi","countAsylum":"0"},{"country":"Belgium","countAsylum":"0"},{"country":"Central African Rep.","countAsylum":"38","countRefugee":"15"},{"country":"Cote d'Ivoire","countAsylum":"50","countRefugee":"105"},{"country":"Cameroon","countAsylum":"17","countRefugee":"548"},{"country":"Dem. Rep. Congo","countAsylum":"447","countRefugee":"600"},{"country":"Congo","countAsylum":"4","countRefugee":"4"},{"country":"Eritrea","countAsylum":"1","countRefugee":"2"},{"country":"Ethiopia","countAsylum":"2","countRefugee":"1"},{"country":"Ghana","countAsylum":"0","countRefugee":"1"},{"country":"Guinea","countAsylum":"7","countRefugee":"23"},{"country":"Gambia","countAsylum":"0"},{"country":"Guinea-Bissau","countRefugee":"5"},{"country":"Liberia","countAsylum":"4","countRefugee":"123"},{"country":"Sri Lanka","countAsylum":"0"},{"country":"Mali","countAsylum":"135","countRefugee":"98"},{"country":"Palestinian","countAsylum":"1"},{"country":"Rwanda","countAsylum":"0","countRefugee":"1"},{"country":"Sudan","countAsylum":"4","countRefugee":"47"},{"country":"Sierra Leone","countAsylum":"2","countRefugee":"24"},{"country":"Somalia","countRefugee":"2"},{"country":"Syrian Arab Rep.","countAsylum":"10","countRefugee":"9"},{"country":"Chad","countAsylum":"83","countRefugee":"71"},{"country":"Togo","countAsylum":"10","countRefugee":"10"},{"country":"Zambia","countAsylum":"0"}],"2014":[{"country":"Afghanistan","countAsylum":"0","countRefugee":"5"},{"country":"Central African Rep.","countAsylum":"112","countRefugee":"77"},{"country":"Cote d'Ivoire","countAsylum":"52","countRefugee":"108"},{"country":"Cameroon","countAsylum":"11","countRefugee":"162"},{"country":"Dem. Rep. Congo","countAsylum":"348","countRefugee":"531"},{"country":"Congo","countAsylum":"1","countRefugee":"4"},{"country":"Eritrea","countAsylum":"17","countRefugee":"3"},{"country":"Ethiopia","countAsylum":"1","countRefugee":"2"},{"country":"Ghana","countAsylum":"1","countRefugee":"1"},{"country":"Guinea","countAsylum":"5","countRefugee":"17"},{"country":"Guinea-Bissau","countAsylum":"0","countRefugee":"5"},{"country":"Eq. Guinea","countAsylum":"0","countRefugee":"2"},{"country":"Iraq","countAsylum":"1","countRefugee":"0"},{"country":"Lebanon","countAsylum":"4","countRefugee":"0"},{"country":"Liberia","countAsylum":"5","countRefugee":"22"},{"country":"Sri Lanka","countAsylum":"0","countRefugee":"2"},{"country":"Mali","countAsylum":"238","countRefugee":"117"},{"country":"Nigeria","countAsylum":"0","countRefugee":"0"},{"country":"Pakistan","countAsylum":"0","countRefugee":"0"},{"country":"Palestinian","countAsylum":"1","countRefugee":"3"},{"country":"Rwanda","countAsylum":"0","countRefugee":"1"},{"country":"Sudan","countAsylum":"2","countRefugee":"49"},{"country":"Senegal","countAsylum":"1","countRefugee":"0"},{"country":"Sierra Leone","countAsylum":"1","countRefugee":"21"},{"country":"Somalia","countAsylum":"0","countRefugee":"4"},{"country":"Syrian Arab Rep.","countAsylum":"17","countRefugee":"11"},{"country":"Chad","countAsylum":"31","countRefugee":"79"},{"country":"Togo","countAsylum":"7","countRefugee":"13"}],"2015":[{"country":"Afghanistan","countAsylum":"0","countRefugee":"5"},{"country":"Burundi","countAsylum":"0","countRefugee":"8"},{"country":"Benin","countAsylum":"1","countRefugee":"0"},{"country":"Central African Rep.","countAsylum":"50","countRefugee":"149"},{"country":"Cote d'Ivoire","countAsylum":"25","countRefugee":"117"},{"country":"Cameroon","countAsylum":"8","countRefugee":"161"},{"country":"Dem. Rep. Congo","countAsylum":"158","countRefugee":"561"},{"country":"Congo","countAsylum":"0","countRefugee":"4"},{"country":"Eritrea","countAsylum":"12","countRefugee":"14"},{"country":"Ethiopia","countAsylum":"0","countRefugee":"2"},{"country":"Ghana","countAsylum":"1","countRefugee":"3"},{"country":"Guinea","countAsylum":"3","countRefugee":"17"},{"country":"Gambia","countAsylum":"1","countRefugee":"0"},{"country":"Guinea-Bissau","countAsylum":"0","countRefugee":"5"},{"country":"Eq. Guinea","countAsylum":"0","countRefugee":"2"},{"country":"Iraq","countAsylum":"0","countRefugee":"1"},{"country":"Kyrgyzstan","countAsylum":"0","countRefugee":"2"},{"country":"Lebanon","countAsylum":"7","countRefugee":"0"},{"country":"Liberia","countAsylum":"0","countRefugee":"9"},{"country":"Libya","countAsylum":"0","countRefugee":"2"},{"country":"Sri Lanka","countAsylum":"0","countRefugee":"2"},{"country":"Mali","countAsylum":"43","countRefugee":"136"},{"country":"Nigeria","countAsylum":"0","countRefugee":"0"},{"country":"Palestinian","countAsylum":"0","countRefugee":"3"},{"country":"Rwanda","countAsylum":"0","countRefugee":"1"},{"country":"Sudan","countAsylum":"6","countRefugee":"48"},{"country":"Senegal","countAsylum":"1","countRefugee":"0"},{"country":"Sierra Leone","countAsylum":"0","countRefugee":"23"},{"country":"Somalia","countAsylum":"0","countRefugee":"1"},{"country":"Syrian Arab Rep.","countAsylum":"41","countRefugee":"32"},{"country":"Chad","countAsylum":"25","countRefugee":"74"},{"country":"Togo","countAsylum":"4","countRefugee":"13"}],"2016":[{"country":"Afghanistan","countAsylum":"0","countRefugee":"5"},{"country":"Benin","countAsylum":"0","countRefugee":"*"},{"country":"Central African Rep.","countAsylum":"49","countRefugee":"166"},{"country":"Cote d'Ivoire","countAsylum":"25","countRefugee":"118"},{"country":"Cameroon","countAsylum":"15","countRefugee":"29"},{"country":"Dem. Rep. Congo","countAsylum":"202","countRefugee":"571"},{"country":"Congo","countAsylum":"0","countRefugee":"*"},{"country":"Eritrea","countAsylum":"15","countRefugee":"22"},{"country":"Ethiopia","countAsylum":"0","countRefugee":"7"},{"country":"Ghana","countAsylum":"*","countRefugee":"*"},{"country":"Guinea","countAsylum":"5","countRefugee":"17"},{"country":"Gambia","countAsylum":"*","countRefugee":"0"},{"country":"Guinea-Bissau","countAsylum":"0","countRefugee":"5"},{"country":"Eq. Guinea","countAsylum":"0","countRefugee":"*"},{"country":"Iraq","countAsylum":"0","countRefugee":"*"},{"country":"Kyrgyzstan","countAsylum":"0","countRefugee":"*"},{"country":"Lebanon","countAsylum":"7","countRefugee":"*"},{"country":"Liberia","countAsylum":"0","countRefugee":"9"},{"country":"Libya","countAsylum":"0","countRefugee":"*"},{"country":"Sri Lanka","countAsylum":"0","countRefugee":"*"},{"country":"Morocco","countAsylum":"*","countRefugee":"0"},{"country":"Mali","countAsylum":"46","countRefugee":"137"},{"country":"Nigeria","countAsylum":"0","countRefugee":"0"},{"country":"Pakistan","countAsylum":"*","countRefugee":"0"},{"country":"Palestinian","countAsylum":"*","countRefugee":"8"},{"country":"Rwanda","countAsylum":"0","countRefugee":"*"},{"country":"Sudan","countAsylum":"*","countRefugee":"47"},{"country":"Senegal","countAsylum":"*","countRefugee":"0"},{"country":"Sierra Leone","countAsylum":"0","countRefugee":"21"},{"country":"Somalia","countAsylum":"0","countRefugee":"*"},{"country":"Syrian Arab Rep.","countAsylum":"47","countRefugee":"88"},{"country":"Chad","countAsylum":"27","countRefugee":"77"},{"country":"Togo","countAsylum":"16","countRefugee":"20"},{"country":"Turkey","countAsylum":"*","countRefugee":"0"},{"country":"Yemen","countAsylum":"*","countRefugee":"0"}]}